LICENSE
README.md
setup.py
imgur_wesbite_scraper.egg-info/PKG-INFO
imgur_wesbite_scraper.egg-info/SOURCES.txt
imgur_wesbite_scraper.egg-info/dependency_links.txt
imgur_wesbite_scraper.egg-info/requires.txt
imgur_wesbite_scraper.egg-info/top_level.txt
pypi_scraper/__init__.py